fttrade/__init__.py
fttrade/constants.py
fttrade/ft.py
fttrade/ft_fix.py
fttrade/logger.py
fttrade/utils.py
fttrade-0.0.4.dist-info/METADATA
fttrade-0.0.4.dist-info/WHEEL
fttrade-0.0.4.dist-info/top_level.txt
fttrade-0.0.4.dist-info/RECORD
