Metadata-Version: 2.1
Name: fttrade
Version: 0.0.4
Summary: scripts for ft
Home-page: http://www.puyuan.tech
Author: puyuan.tech
Author-email: info@puyuan.tech
Maintainer: puyuan_staff
Maintainer-email: github@puyuan.tech
License: MIT License
Platform: all
Classifier: Development Status :: 4 - Beta
Classifier: Operating System :: OS Independent
Classifier: Intended Audience :: Developers
Classifier: License :: OSI Approved :: MIT License
Classifier: Programming Language :: Python
Classifier: Programming Language :: Python :: Implementation
Classifier: Programming Language :: Python :: 2
Classifier: Programming Language :: Python :: 2.7
Classifier: Topic :: Software Development :: Libraries
Requires-Dist: pymongo (==3.9.0requestswebsocket-client)
